{
  "project_info": {
    "project_number": "683258039602",
    "project_id": "jediprojects-afa82",
    "storage_bucket": "jediprojects-afa82.appspot.com"
  },
  "client": [
    {
      "client_info": {
        "mobilesdk_app_id": "1:683258039602:android:71cf10f5898c68e47d1b2b",
        "android_client_info": {
          "package_name": "br.com.unside.jediprojects"
        }
      },
      "oauth_client": [
        {
          "client_id": "683258039602-ufk8uqdri0argf0d4ks3gcidfnnequgo.apps.googleusercontent.com",
          "client_type": 3
        }
      ],
      "api_key": [
        {
          "current_key": "AIzaSyC0A3MvEm4Iau4-GbTxb-kQOQsP8zjIW00"
        }
      ],
      "services": {
        "appinvite_service": {
          "other_platform_oauth_client": [
            {
              "client_id": "683258039602-ufk8uqdri0argf0d4ks3gcidfnnequgo.apps.googleusercontent.com",
              "client_type": 3
            }
          ]
        }
      }
    }
  ],
  "configuration_version": "1"
}